envsettings/database.py
envsettings/base.py
envsettings/__init__.py
envsettings/email.py
envsettings/cache.py
django_envsettings-1.1.0.dist-info/top_level.txt
django_envsettings-1.1.0.dist-info/METADATA
django_envsettings-1.1.0.dist-info/DESCRIPTION.rst
django_envsettings-1.1.0.dist-info/metadata.json
django_envsettings-1.1.0.dist-info/WHEEL
django_envsettings-1.1.0.dist-info/RECORD
