Metadata-Version: 2.0
Name: django-envsettings
Version: 1.1.0
Summary: One-stop shop for configuring 12-factor Django apps
Home-page: http://github.com/evansd/django-envsettings
Author: David Evans
Author-email: d@evans.io
License: MIT
Platform: UNKNOWN
Classifier: Development Status :: 5 - Production/Stable
Classifier: Framework :: Django
Classifier: Intended Audience :: Developers
Classifier: License :: OSI Approved :: MIT License
Classifier: Operating System :: OS Independent
Classifier: Programming Language :: Python :: 2.7
Classifier: Programming Language :: Python :: 3.3
Classifier: Programming Language :: Python :: 3.4
